simplejsonspider/__init__.py
simplejsonspider/spider.py
simplejsonspider-0.2.2.dist-info/LICENSE
simplejsonspider-0.2.2.dist-info/METADATA
simplejsonspider-0.2.2.dist-info/WHEEL
simplejsonspider-0.2.2.dist-info/top_level.txt
simplejsonspider-0.2.2.dist-info/RECORD
